NewsTone/CNN_Model.py
NewsTone/Classification_Test.py
NewsTone/Classification_Train.py
NewsTone/Data_Preprocess.py
NewsTone/Data_Split.py
NewsTone/NewsTone.py
NewsTone/Visualization.py
NewsTone/__init__.py
NewsTone/config.py
NewsTone/preprocess.py
NewsTone/test.py
NewsTone/train.py
NewsTone/utils.py
NewsTone-0.135.dist-info/METADATA
NewsTone-0.135.dist-info/WHEEL
NewsTone-0.135.dist-info/top_level.txt
NewsTone-0.135.dist-info/RECORD
