Metadata-Version: 2.1
Name: NewsTone
Version: 0.135
Summary: Sentimental Analysis
Home-page: https://github.com/indexxlim/NewsTone
Author-email: indexxlim@gmail.com
License: UNKNOWN
Keywords: Sentimental,Positive,Negative
Platform: UNKNOWN
Requires-Python: >=3.5
Requires-Dist: NumPy (>=1.11.0)
Requires-Dist: SciPy (>=0.17.0)
Requires-Dist: joblib (>=0.11)
Requires-Dist: scikit-learn
Requires-Dist: tqdm
Requires-Dist: pandas
Requires-Dist: gensim
Requires-Dist: konlpy
Requires-Dist: xlrd
